aiphad/__init__.py
aiphad/aiphad.py
aiphad/aiphad_output.py
aiphad-1.0.1.dist-info/METADATA
aiphad-1.0.1.dist-info/WHEEL
aiphad-1.0.1.dist-info/top_level.txt
aiphad-1.0.1.dist-info/RECORD
